{
  "season": 8,
  "game": 17,
  "opponent": "LIGHTNING 1",
  "opponentColor": "#F9CB49",
  "teamScore": 43.0,
  "opponentScore": 69.0,
  "players": [
    {
      "NAMES": "Lachlan Farley",
      "2PM": 1.0,
      "2PA": 13.0,
      "3PM": 0.0,
      "3PA": 4.0,
      "FGM": 1.0,
      "FGA": 17.0,
      "FTM": 7.0,
      "FTA": 10.0,
      "O REB": 4.0,
      "D REB": 3.0,
      "PTS": 9,
      "REB": 7.0,
      "AST": 0.0,
      "BLK": 0.0,
      "STL": 0.0,
      "TOV": 5.0,
      "FLS": 2.0,
      "FG%": 0.058823529411764705,
      "FT%": 0.7,
      "2P%": 0.07692307692307693,
      "3P%": 0.0,
      "GSC": -5.799999999999999,
      "TS%": 0.21028037383177572,
      "rowColor": "#FF99CC",
      "FG%_display": "5.88%",
      "TS%_display": "21.03%",
      "2P%_display": "7.69%",
      "3P%_display": "0.00%",
      "FT%_display": "70.00%",
      "2PM_display": "1",
      "2PA_display": "13",
      "3PM_display": "0",
      "3PA_display": "4",
      "FGM_display": "1",
      "FGA_display": "17",
      "FTM_display": "7",
      "FTA_display": "10",
      "O REB_display": "4",
      "D REB_display": "3",
      "PTS_display": "9",
      "REB_display": "7",
      "AST_display": "0",
      "BLK_display": "0",
      "STL_display": "0",
      "TOV_display": "5",
      "FLS_display": "2",
      "GSC_display": "-5.80"
    },
    {
      "NAMES": "Harry Coller",
      "2PM": 6.0,
      "2PA": 16.0,
      "3PM": 3.0,
      "3PA": 10.0,
      "FGM": 9.0,
      "FGA": 26.0,
      "FTM": 2.0,
      "FTA": 2.0,
      "O REB": 4.0,
      "D REB": 6.0,
      "PTS": 23,
      "REB": 10.0,
      "AST": 1.0,
      "BLK": 0.0,
      "STL": 1.0,
      "TOV": 2.0,
      "FLS": 3.0,
      "FG%": 0.34615384615384615,
      "FT%": 1.0,
      "2P%": 0.375,
      "3P%": 0.3,
      "GSC": 11.500000000000004,
      "TS%": 0.427827380952381,
      "rowColor": "#5f99f5",
      "FG%_display": "34.62%",
      "TS%_display": "42.78%",
      "2P%_display": "37.50%",
      "3P%_display": "30.00%",
      "FT%_display": "100.00%",
      "2PM_display": "6",
      "2PA_display": "16",
      "3PM_display": "3",
      "3PA_display": "10",
      "FGM_display": "9",
      "FGA_display": "26",
      "FTM_display": "2",
      "FTA_display": "2",
      "O REB_display": "4",
      "D REB_display": "6",
      "PTS_display": "23",
      "REB_display": "10",
      "AST_display": "1",
      "BLK_display": "0",
      "STL_display": "1",
      "TOV_display": "2",
      "FLS_display": "3",
      "GSC_display": "11.50"
    },
    {
      "NAMES": "Adam Blain",
      "2PM": 2.0,
      "2PA": 11.0,
      "3PM": 1.0,
      "3PA": 4.0,
      "FGM": 3.0,
      "FGA": 15.0,
      "FTM": 0.0,
      "FTA": 1.0,
      "O REB": 3.0,
      "D REB": 17.0,
      "PTS": 7,
      "REB": 20.0,
      "AST": 2.0,
      "BLK": 3.0,
      "STL": 1.0,
      "TOV": 2.0,
      "FLS": 2.0,
      "FG%": 0.2,
      "FT%": 0.0,
      "2P%": 0.18181818181818182,
      "3P%": 0.25,
      "GSC": 6.1999999999999975,
      "TS%": 0.2266839378238342,
      "rowColor": "#be60f7",
      "FG%_display": "20.00%",
      "TS%_display": "22.67%",
      "2P%_display": "18.18%",
      "3P%_display": "25.00%",
      "FT%_display": "0.00%",
      "2PM_display": "2",
      "2PA_display": "11",
      "3PM_display": "1",
      "3PA_display": "4",
      "FGM_display": "3",
      "FGA_display": "15",
      "FTM_display": "0",
      "FTA_display": "1",
      "O REB_display": "3",
      "D REB_display": "17",
      "PTS_display": "7",
      "REB_display": "20",
      "AST_display": "2",
      "BLK_display": "3",
      "STL_display": "1",
      "TOV_display": "2",
      "FLS_display": "2",
      "GSC_display": "6.20"
    },
    {
      "NAMES": "Lachlan Farrugia",
      "2PM": 1.0,
      "2PA": 3.0,
      "3PM": 0.0,
      "3PA": 2.0,
      "FGM": 1.0,
      "FGA": 5.0,
      "FTM": 2.0,
      "FTA": 2.0,
      "O REB": 0.0,
      "D REB": 5.0,
      "PTS": 4,
      "REB": 5.0,
      "AST": 1.0,
      "BLK": 0.0,
      "STL": 2.0,
      "TOV": 3.0,
      "FLS": 4.0,
      "FG%": 0.2,
      "FT%": 1.0,
      "2P%": 0.3333333333333333,
      "3P%": 0.0,
      "GSC": 0.5000000000000004,
      "TS%": 0.3401360544217687,
      "rowColor": "#5cf046",
      "FG%_display": "20.00%",
      "TS%_display": "34.01%",
      "2P%_display": "33.33%",
      "3P%_display": "0.00%",
      "FT%_display": "100.00%",
      "2PM_display": "1",
      "2PA_display": "3",
      "3PM_display": "0",
      "3PA_display": "2",
      "FGM_display": "1",
      "FGA_display": "5",
      "FTM_display": "2",
      "FTA_display": "2",
      "O REB_display": "0",
      "D REB_display": "5",
      "PTS_display": "4",
      "REB_display": "5",
      "AST_display": "1",
      "BLK_display": "0",
      "STL_display": "2",
      "TOV_display": "3",
      "FLS_display": "4",
      "GSC_display": "0.50"
    },
    {
      "NAMES": "Panthers",
      "2PM": 10.0,
      "2PA": 43.0,
      "3PM": 4.0,
      "3PA": 20.0,
      "FGM": 14.0,
      "FGA": 63.0,
      "FTM": 11.0,
      "FTA": 15.0,
      "O REB": 11.0,
      "D REB": 31.0,
      "PTS": 43,
      "REB": 42.0,
      "AST": 4.0,
      "BLK": 3.0,
      "STL": 4.0,
      "TOV": 12.0,
      "FLS": 11.0,
      "FG%": 0.2222222222222222,
      "FT%": 0.7333333333333333,
      "2P%": 0.23255813953488372,
      "3P%": 0.2,
      "GSC": 3.1000000000000005,
      "TS%": 0.30890804597701155,
      "rowColor": "#f07c29",
      "FG%_display": "22.22%",
      "TS%_display": "30.89%",
      "2P%_display": "23.26%",
      "3P%_display": "20.00%",
      "FT%_display": "73.33%",
      "2PM_display": "10",
      "2PA_display": "43",
      "3PM_display": "4",
      "3PA_display": "20",
      "FGM_display": "14",
      "FGA_display": "63",
      "FTM_display": "11",
      "FTA_display": "15",
      "O REB_display": "11",
      "D REB_display": "31",
      "PTS_display": "43",
      "REB_display": "42",
      "AST_display": "4",
      "BLK_display": "3",
      "STL_display": "4",
      "TOV_display": "12",
      "FLS_display": "11",
      "GSC_display": "3.10"
    }
  ]
}